streamlit_report/__init__.py
streamlit_report/htmlClass.py
streamlit_report/report.py
streamlit_report/style.html
streamlit_report-0.0.7.dist-info/LICENSE
streamlit_report-0.0.7.dist-info/METADATA
streamlit_report-0.0.7.dist-info/WHEEL
streamlit_report-0.0.7.dist-info/RECORD
