Metadata-Version: 2.3
Name: streamlit-report
Version: 0.0.7
Summary: 
Author: Nick Xydis
Author-email: nsxydis@gmail.com
Requires-Python: >=3.9
Classifier: Programming Language :: Python :: 3
Classifier: Programming Language :: Python :: 3.9
Classifier: Programming Language :: Python :: 3.10
Classifier: Programming Language :: Python :: 3.11
Classifier: Programming Language :: Python :: 3.12
Classifier: Programming Language :: Python :: 3.13
Requires-Dist: altair
Requires-Dist: markdown
Requires-Dist: polars
Requires-Dist: streamlit
